pwned_passwords_django-5.1.3.dist-info/METADATA
pwned_passwords_django-5.1.3.dist-info/WHEEL
pwned_passwords_django-5.1.3.dist-info/entry_points.txt
pwned_passwords_django-5.1.3.dist-info/licenses/LICENSE
pwned_passwords_django/__init__.py
pwned_passwords_django/api.py
pwned_passwords_django/exceptions.py
pwned_passwords_django/middleware.py
pwned_passwords_django/validators.py
pwned_passwords_django-5.1.3.dist-info/RECORD
