Metadata-Version: 2.1
Name: pwned-passwords-django
Version: 5.1.3
Summary: A Pwned Passwords implementation for Django sites.
Keywords: django,security,passwords,auth,authentication
Author: James Bennett
License: BSD-3-Clause
Classifier: Development Status :: 5 - Production/Stable
Classifier: Environment :: Web Environment
Classifier: Framework :: Django
Classifier: Framework :: Django :: 4.2
Classifier: Framework :: Django :: 5.0
Classifier: Framework :: Django :: 5.1
Classifier: Intended Audience :: Developers
Classifier: License :: OSI Approved :: BSD License
Classifier: Operating System :: OS Independent
Classifier: Programming Language :: Python
Classifier: Programming Language :: Python :: 3
Classifier: Programming Language :: Python :: 3.9
Classifier: Programming Language :: Python :: 3.10
Classifier: Programming Language :: Python :: 3.11
Classifier: Programming Language :: Python :: 3.12
Classifier: Programming Language :: Python :: 3.13
Classifier: Topic :: Utilities
Project-URL: Documentation, https://pwned-passwords-django.readthedocs.io/
Project-URL: Source Code, https://github.com/ubernostrum/pwned-passwords-django
Requires-Python: >=3.9
Requires-Dist: Django>=4.2
Requires-Dist: httpx
